edf_api/__init__.py
edf_api/auth.py
edf_api/const.py
edf_api/exc.py
edf_api/models.py
edf_api-1.0.0.dist-info/LICENCE
edf_api-1.0.0.dist-info/METADATA
edf_api-1.0.0.dist-info/WHEEL
edf_api-1.0.0.dist-info/top_level.txt
edf_api-1.0.0.dist-info/RECORD
