Metadata-Version: 2.1
Name: edf-api
Version: 1.0.0
Summary: API for EDF
Home-page: https://github.com/droso-hass/edf-api
Author: drosocode
License: MIT
Project-URL: Documentation, https://edf-api.readthedocs.io/en/latest/
Project-URL: Source, https://github.com/droso-hass/edf-api
Platform: UNKNOWN
Classifier: Programming Language :: Python :: 3
Classifier: License :: OSI Approved :: MIT License
Classifier: Operating System :: OS Independent
Requires-Python: >=3.7
License-File: LICENCE
Requires-Dist: aiohttp
Requires-Dist: async-timeout
Requires-Dist: lxml
